ldfparser/__init__.py
ldfparser/cli.py
ldfparser/diagnostics.py
ldfparser/encoding.py
ldfparser/frame.py
ldfparser/grammar.py
ldfparser/ldf.py
ldfparser/lin.py
ldfparser/node.py
ldfparser/parser.py
ldfparser/save.py
ldfparser/schedule.py
ldfparser/signal.py
ldfparser/grammars/__init__.py
ldfparser/grammars/ldf.lark
ldfparser/templates/__init__.py
ldfparser-0.26.0.dist-info/LICENSE
ldfparser-0.26.0.dist-info/METADATA
ldfparser-0.26.0.dist-info/WHEEL
ldfparser-0.26.0.dist-info/entry_points.txt
ldfparser-0.26.0.dist-info/top_level.txt
ldfparser-0.26.0.dist-info/RECORD
