Metadata-Version: 2.1
Name: ldfparser
Version: 0.26.0
Summary: LDF Language support for Python
Home-page: https://github.com/c4deszes/ldfparser
Author: Balazs Eszes
Author-email: c4deszes@gmail.com
License: MIT
Project-URL: Documentation, https://c4deszes.github.io/ldfparser/
Project-URL: Source Code, https://github.com/c4deszes/ldfparser
Keywords: LIN,LDF
Platform: UNKNOWN
Classifier: Programming Language :: Python :: 3.6
Classifier: Programming Language :: Python :: 3.7
Classifier: Programming Language :: Python :: 3.8
Classifier: Programming Language :: Python :: 3.9
Classifier: License :: OSI Approved :: MIT License
Classifier: Operating System :: OS Independent
Requires-Python: !=3.0.*, !=3.1.*, !=3.2.*, !=3.3.*, !=3.4.*, !=3.5.*, <4
Provides-Extra: dev
License-File: LICENSE
